{"show_name": "Dragon Ball: Super Saiya-jin Zetsumetsu Keikaku", "other_title": ["Dragon Ball Z: Plan to Eradicate Super Saiyans OVA Remake", "\u30c9\u30e9\u30b4\u30f3\u30dc\u30fc\u30eb\u3000\u8d85\u30b5\u30a4\u30e4\u4eba\u7d76\u6ec5\u8a08\u753b"], "genre": ["Sci-Fi", "Adventure", "Super Power", "Martial Arts", "Fantasy", "Shounen"], "type": "ova", "plot": "", "episode": 1, "vintage": "2010-11-11 - 2010-11-11", "opening_theme": [], "ending_theme": [], "image": "https://api-cdn.myanimelist.net/images/anime/8/56931.jpg"}