{"show_name": "Ie Naki Ko Remy Specials (2001)", "other_title": ["Ie Naki Ko R\u00e9mi Specials (2001)", "Sekai Meisaku Gekijou Kanketsu Ban: Ie Naki Ko Remi", "World Masterpiece Theater Complete Edition: Homeless Child Remy", "Nobody's Girl Remi", "Remi the Homeless Girl", "\u4e16\u754c\u540d\u4f5c\u5287\u5834\u30fb\u5b8c\u7d50\u7248 \u5bb6\u306a\u304d\u5b50\u30ec\u30df"], "genre": ["Adventure", "Slice of Life", "Drama"], "type": "special", "plot": "", "episode": 2, "vintage": "2001-07-14 - 2001-07-15", "opening_theme": [], "ending_theme": [], "image": "https://api-cdn.myanimelist.net/images/anime/11/64147.jpg"}