{"show_name": "Di Gi Charat Nyo", "other_title": ["DiGi Charat Nyo", "\u30c7\u30fb\u30b8\u30fb\u30ad\u30e3\u30e9\u30c3\u30c8\u306b\u3087"], "genre": ["Comedy", "Fantasy", "Sci-Fi"], "type": "tv", "plot": "", "episode": 104, "vintage": "2003-04-06 - 2004-03-28", "opening_theme": ["#1: \"Heartbeat\" by Pri\u00e8re", "#2: \"Dynamite I.N.G (\u30c0\u30a4\u30ca\u30de\u30a4\u30c8\u2605\uff29\u30fb\uff2e\u30fb\uff27)\" by Asami Sanada, Miyuki Sawashiro, and Kyoko Hikami", "#3: \"Miracle Wonderland (\u30df\u30e9\u30af\u30eb\u2606\u30ef\u30f3\u30c0\u30fc\u30e9\u30f3\u30c9)\" by Asami Sanada, Miyuki Sawashiro, and Kyoko Hikami"], "ending_theme": ["#1: \"EQUAL \u30ed\u30de\u30f3\u30b9 (Equal Romance)\" by Pri\u00e8re", "#2: \"Di Gi Charat Ondo (\u30c7\u30fb\u30b8\u30fb\u30ad\u30e3\u30e9\u30c3\u30c8\u97f3\u982d)\" by Asami Sanada, Miyuki Sawashiro, Kyoko Hikami, and Yoshik", "#3: \"PARTY\u2606NIGHT -Cyber Trance Version-\" by Asami Sanada, Miyuki Sawashiro, Kyoko Hikami, and Yuka Iguchi", "#4: \"PARTY\u2606NIGHT -Cyber X'mas Version-\" by Asami Sanada, Miyuki Sawashiro, Kyoko Hikami, and Yuka Iguchi", "#5: \"Daisuki (\u30c0\u30a4\u30b9\u30ad)\" by Asami Sanada, Miyuki Sawashiro, and Kyoko Hikami"], "image": "https://api-cdn.myanimelist.net/images/anime/2/57015.jpg"}