{"show_name": "Tottoko Hamtarou Movie 1: Ham-Ham Land Daibouken", "other_title": ["Hamtaro the Movie", "Hamutarou", "Hamtaro Movie 1: Ham Ham Land Big Adventure", "\u3068\u3063\u3068\u3053\u30cf\u30e0\u592a\u90ce \u30cf\u30e0\u30cf\u30e0\u30e9\u30f3\u30c9\u5927\u5192\u967a"], "genre": ["Kids", "Adventure", "Comedy"], "type": "movie", "plot": "", "episode": 1, "vintage": "2001-12-15 - 2001-12-15", "opening_theme": ["\"Minihamus no Ai no Uta (\u30df\u30cb\u30cf\u30e0\u305a\u306e\u611b\u306e\u5504)\" by Minimoni. (\u30df\u30cb\u30e2\u30cb\u3002)"], "ending_theme": [], "image": "https://api-cdn.myanimelist.net/images/anime/9/17422.jpg"}