{"show_name": "Gakusen Toshi Asterisk", "other_title": ["Academy Battle City Asterisk", "The Asterisk War", "\u5b66\u6226\u90fd\u5e02\u30a2\u30b9\u30bf\u30ea\u30b9\u30af"], "genre": ["Action", "Comedy", "Ecchi", "Fantasy", "Harem", "Romance", "School", "Sci-Fi", "Supernatural"], "type": "tv", "plot": "", "episode": 12, "vintage": "2015-10-03 - 2015-12-19", "opening_theme": ["\"Brand-new World\" by Shiena Nishizawa (eps 2-11)"], "ending_theme": ["#1: \"Brand-new World\" by Shiena Nishizawa (ep 1)", "#2: \"Waiting for the rain\" by Maaya Sakamoto (eps 2-12)"], "image": "https://api-cdn.myanimelist.net/images/anime/5/76034.jpg"}