{"show_name": "Usakame Special", "other_title": ["\u3046\u3055\u304b\u3081"], "genre": ["Comedy", "Sports", "Shounen"], "type": "special", "plot": "", "episode": 1, "vintage": "2016-08-26 - 2016-08-26", "opening_theme": ["\"Hashire! Usakame Koukou Tennis-bu!! (\u8d70\u308c\uff01\u3046\u3055\u304b\u3081\u9ad8\u6821\u30c6\u30cb\u30b9\u90e8!!)\" by Usakame Koukou Tennis-bu (Yuki Nakashima, Hikaru Koide, Izumi Araida, Maria Tanijiri)"], "ending_theme": ["\"Promise you\" by Earth Star Dream"], "image": "https://api-cdn.myanimelist.net/images/anime/9/83507.jpg"}