{"show_name": "Haikyuu!! Movie 4: Concept no Tatakai", "other_title": ["High Kyuu!! Movie 4: Haikyuu!! Movie 4: Battle of Concepts", "Haikyuu!!: Karasuno Koukou VS Shiratorizawa Gakuen Koukou Recap", "Haikyuu!! Recap 4", "\u30cf\u30a4\u30ad\u30e5\u30fc!! \u30b3\u30f3\u30bb\u30d7\u30c8\u306e\u6226\u3044"], "genre": ["Comedy", "Drama", "School", "Shounen", "Sports"], "type": "movie", "plot": "", "episode": 1, "vintage": "2017-09-29 - 2017-09-29", "opening_theme": [], "ending_theme": ["\"Hikari Are (\u30d2\u30ab\u30ea\u30a2\u30ec)\" by BURNOUT SYNDROMES"], "image": "https://api-cdn.myanimelist.net/images/anime/3/86346.jpg"}