{"show_name": "The iDOLM@STER Cinderella Girls 2nd Anniversary PV", "other_title": ["The Idolmaster Cinderella Girls: Onegai Cinderella", "THE IDOLM@STER CINDERELLA GIRLS 2nd ANNIVERSARY PV", "\u30a2\u30a4\u30c9\u30eb\u30de\u30b9\u30bf\u30fc \u30b7\u30f3\u30c7\u30ec\u30e9\u30ac\u30fc\u30eb\u30ba \uff12\u5468\u5e74\u8a18\u5ff5\uff30\uff36"], "genre": ["Music"], "type": "music", "plot": "", "episode": 1, "vintage": "2013-11-28 - 2013-11-28", "opening_theme": [], "ending_theme": [], "image": "https://api-cdn.myanimelist.net/images/anime/3/67139.jpg"}