{"show_name": "Super Robot Taisen OG: Divine Wars", "other_title": ["Super Robot Wars OG: Divine Wars", "SRWOG", "Super Robot Wars The Original Generation: The Divine Wars", "\u30b9\u30fc\u30d1\u30fc\u30ed\u30dc\u30c3\u30c8\u5927\u6226OG -\u30c7\u30a3\u30d0\u30a4\u30f3\u30fb\u30a6\u30a9\u30fc\u30ba-"], "genre": ["Action", "Mecha", "Sci-Fi"], "type": "tv", "plot": "", "episode": 25, "vintage": "2006-10-05 - 2007-03-29", "opening_theme": ["#1: \"Break Out\" by JAM Project (eps 1-17, 24-25)", "#2: \"Rising Force\" by JAM Project (eps 18-23)"], "ending_theme": ["#1: \"Yell!\" by Minami Kuribayashi (eps 1-13)", "#2: \"Mou Ai Shika Iranai\" by Aki Misato (eps 14-25)"], "image": "https://api-cdn.myanimelist.net/images/anime/7/31063.jpg"}