{"show_name": "Vexille: 2077 Nihon Sakoku", "other_title": ["Vexille: 2077 Nippon Sakoku", "Vexille: 2077 Japan National Isolation", "Vexille", "\u30d9\u30af\u30b7\u30eb 2077\u65e5\u672c\u9396\u56fd"], "genre": ["Action", "Military", "Sci-Fi"], "type": "movie", "plot": "", "episode": 1, "vintage": "2007-08-18 - 2007-08-18", "opening_theme": ["\"Close Your Eyes\" by Basement Jaxx"], "ending_theme": ["\"Together Again\" by mink"], "image": "https://api-cdn.myanimelist.net/images/anime/9/79923.jpg"}