{"show_name": "Code Geass: Hangyaku no Lelouch III - Oudou", "other_title": ["Code Geass: Lelouch of the Rebellion - Emperor", "Code Geass: Lelouch of the Rebellion III - Glorification", "\u30b3\u30fc\u30c9\u30ae\u30a2\u30b9 \u53cd\u9006\u306e\u30eb\u30eb\u30fc\u30b7\u30e5\u2162 \u7687\u9053"], "genre": ["Action", "Mecha", "Military", "School", "Sci-Fi", "Super Power"], "type": "movie", "plot": "", "episode": 1, "vintage": "2018-05-26 - 2018-05-26", "opening_theme": ["\"WORLD END\" by FLOW"], "ending_theme": ["\"NE:ONE\" by Survive Said The Prophet"], "image": "https://api-cdn.myanimelist.net/images/anime/1126/91344.jpg"}