{"show_name": "Ashita no Joe 2", "other_title": ["Tomorrow's Joe 2", "Rocky Joe 2", "\u3042\u3057\u305f\u306e\u30b8\u30e7\u30fc\uff12"], "genre": ["Action", "Drama", "Shounen", "Slice of Life", "Sports"], "type": "tv", "plot": "", "episode": 47, "vintage": "1980-10-13 - 1981-08-31", "opening_theme": ["#1: \"Kizudarake no Eikou\" by Takeshi Obo (eps 1-25)", "#2: \"MIDNIGHT BLUES\" by Ichiro Araki (eps 26-47)"], "ending_theme": ["#1: \"Hateshinaki Yami no Kanata ni\" by Takeshi Obo (eps 1-25)", "#2: \"Hateshinaki Yami no Kanata ni\" by Ichiro Araki (eps 26-47)"], "image": "https://api-cdn.myanimelist.net/images/anime/3/45028.jpg"}