{"show_name": "Binan Koukou Chikyuu Boueibu LOVE!", "other_title": ["Cute High Earth Defense Club LOVE!", "\u7f8e\u7537\u9ad8\u6821\u5730\u7403\u9632\u885b\u90e8LOVE!"], "genre": ["Slice of Life", "Comedy", "Parody", "Magic", "School"], "type": "tv", "plot": "", "episode": 12, "vintage": "2015-01-07 - 2015-03-25", "opening_theme": ["\"Zettai Muteki\u2606Fallin' LOVE\u2606 (\u7d76\u5bfe\u7121\u6575\u2606Fallin' LOVE\u2606)\" by Chikyuu Bouei-bu (Kazutomi Yamamoto, Yuuichirou Umehara, Toshiki Masuda, Koutarou Nishiyama, Yuusuke Shirai) (eps 2-11)"], "ending_theme": ["#1: \"Zettai Muteki\u2606Fallin' LOVE\u2606 (\u7d76\u5bfe\u7121\u6575\u2606Fallin' LOVE\u2606)\" by Chikyuu Bouei-bu (Kazutomi Yamamoto, Yuuichirou Umehara, Toshiki Masuda, Koutarou Nishiyama, Yuusuke Shirai) (eps 1, 12)", "#2: \"I miss you no 3 meters (I miss you \u306e\uff13\u30e1\u30fc\u30c8\u30eb)\" by Chikyuu Seifuku-bu (Takuma Terashima, Hiroshi Kamiya, Jun Fukuyama) (eps 2-11)"], "image": "https://api-cdn.myanimelist.net/images/anime/10/68451.jpg"}