{"show_name": "Hello World", "other_title": ["\u30cf\u30ed\u30fc\u30fb\u30ef\u30fc\u30eb\u30c9"], "genre": ["Sci-Fi", "Drama", "Romance"], "type": "movie", "plot": "", "episode": 1, "vintage": "2019-09-20 - 2019-09-20", "opening_theme": ["\"Opening Theme feat. AAAMYYY (\u30aa\u30fc\u30d7\u30cb\u30f3\u30b0\u30c6\u30fc\u30de feat.AAAMYYY)\" by Okamoto Sho, Okamoto Kouki featuring AAAMYYY"], "ending_theme": ["\"Shinsekai (\u65b0\u4e16\u754c)\" by OKAMOTO'S"], "image": "https://api-cdn.myanimelist.net/images/anime/1395/102089.jpg"}