{"show_name": "Meme Iroiro Yume no Tabi", "other_title": ["The Traveller of Many Dreams", "Mimu", "Miimu Iro Iro Yume no Tabi", "Discoveries Unlimited", "The Many Dream Journeys of Meme", "\u30df\u30fc\u30e0\u3044\u308d\u3044\u308d\u5922\u306e\u65c5"], "genre": ["Adventure", "Kids", "Sci-Fi"], "type": "tv", "plot": "", "episode": 127, "vintage": "1983-04-03 - 1985-09-29", "opening_theme": ["\"Pocket Uchuu\" by Satoko Yamano, Columbia Yurikagokai"], "ending_theme": [], "image": "https://api-cdn.myanimelist.net/images/anime/2/53527.jpg"}