{"show_name": "Carole & Tuesday: Gus to Roddy no Kaisouroku", "other_title": ["Carole & Tuesday Recap", "Carole & Tuesday Episode 12.5", "\u300c\u30ad\u30e3\u30ed\u30eb\uff06\u30c1\u30e5\u30fc\u30ba\u30c7\u30a4\u300d\u7279\u5225\u7de8 ~\u30ac\u30b9\u3068\u30ed\u30c7\u30a3\u306e\u56de\u60f3\u9332~"], "genre": ["Sci-Fi", "Music", "Drama", "Romance"], "type": "special", "plot": "", "episode": 1, "vintage": "2019-07-04 - 2019-07-04", "opening_theme": ["\"Kiss Me\" by Carole & Tuesday (Nai Br.XX & Celeina Ann)"], "ending_theme": ["\"Hold Me Now\" by Carole & Tuesday (Nai Br.XX & Celeina Ann)"], "image": "https://api-cdn.myanimelist.net/images/anime/1992/101941.jpg"}