{"show_name": "Ojisan to Marshmallow: Hige-san to Yume Mashmallow", "other_title": ["Ojisan and Marshmallow Episode 13: Hige-san and Marshmallow", "\u304a\u3058\u3055\u3093\u3068\u30de\u30b7\u30e5\u30de\u30ed 13\u500b\u76ee \u65e5\u4e0b\u3055\u3093\u3068\u5922\u30de\u30b7\u30e5\u30de\u30ed"], "genre": ["Comedy"], "type": "special", "plot": "", "episode": 1, "vintage": "2016-04-16 - 2016-04-16", "opening_theme": [], "ending_theme": [], "image": "https://api-cdn.myanimelist.net/images/anime/6/79780.jpg"}