{"show_name": "Saint Beast: Ikusen no Hiru to Yoru-hen", "other_title": ["\u30bb\u30a4\u30f3\u30c8\u30fb\u30d3\u30fc\u30b9\u30c8\uff5e\u5e7e\u5343\u306e\u663c\u3068\u591c \u7de8\uff5e"], "genre": ["Magic", "Fantasy"], "type": "ova", "plot": "", "episode": 2, "vintage": "2005-12-17 - 2006-03-18", "opening_theme": ["\"KIZUNA & SADAME\" by Toshiyuki Morikawa, Takahiro Sakurai, Kouki Miyata, Hiroyuki Yoshino"], "ending_theme": ["#1: \"Ikusen no Hiru to Yoru\" by Hikaru Midorikawa, Kouki Miyata, Hiroyuki Yoshino", "#2: \"Kokoro no Kaeru Basho\" by Sakurai Takahiro, Ishida Akira, Toshiyuki Morikawa"], "image": "https://api-cdn.myanimelist.net/images/anime/3/83179.jpg"}