{"show_name": "Gift: Eternal Rainbow - Ki no Saka Ryokan Kiki Ippatsu!!", "other_title": ["Gift: Eternal Rainbow Special", "Gift Eternal Rainbow: Another Gift! - Crisis at the Konosaka Inn!!", "\u30ae\u30d5\u30c8\uff5eeternal rainbow\uff5e \u6728\u4e4b\u5742\u65c5\u9928 \u5371\u6a5f\u4e00\u9aea!!"], "genre": ["Harem", "Comedy", "Magic", "Romance", "Ecchi"], "type": "special", "plot": "", "episode": 1, "vintage": "2007-06-22 - 2007-06-22", "opening_theme": ["\"Nijiiro Sentimental\" by Miyuki Hashimoto"], "ending_theme": ["\"Kokoro Niji o Kakete\" by Misato Fujiya"], "image": "https://api-cdn.myanimelist.net/images/anime/13/25446.jpg"}