{"show_name": "Boku no Imouto wa \"Osaka Okan\"", "other_title": ["Boku no Imouto wa \"Oosaka Okan\"", "\u50d5\u306e\u59b9\u306f\u300c\u5927\u962a\u304a\u304b\u3093\u300d"], "genre": ["Comedy"], "type": "tv", "plot": "", "episode": 12, "vintage": "2012-12-22 - 2013-03-16", "opening_theme": [], "ending_theme": ["#01: \"Osaka Beautiful Name (\u5927\u962a\u30d3\u30e5\u30fc\u30c6\u30a3\u30d5\u30eb\u30fb\u30cd\u30fc\u30e0)\" by Kana Asumi (ep 1)", "#02: \"I'm proud Osaka (I'm proud \u5927\u962a)\" by Kana Asumi (ep 2)", "#03: \"Sasubee wa Itsumo Ame (\u3055\u3059\u3079\u3048\u306f\u3044\u3064\u3082\u96e8)\" by Kana Asumi (ep 3)", "#04: \"Namiwa no Love Song (\u6d6a\u82b1\u306e\u30e9\u30d6\u30bd\u30f3\u30b0)\" by Kana Asumi (ep 4)", "#05: \"Hanshin no Omoide ga Ippai\" (\u962a\u795e\u306e\u601d\u3044\u51fa\u304c\u3044\u3063\u3071\u3044)\" by Kana Asumi (ep 5)", "#06: \"Negiri no Ballad (\u5024\u5207\u308a\u306e\u30d0\u30e9\u30fc\u30c9)\" by Kana Asumi (ep 6)", "#07: \"Kiyou yo Doubutsu Gara no Fuku (\u304d\u3088\u3046\u3088 \u3069\u3046\u3076\u3064\u67c4\u306e\u670d)\" by Kana Asumi (ep 7)", "#08: \"Jikai Yokoku no Uta (\u6b21\u56de\u4e88\u544a\u306e\u6b4c)\" by Kana Asumi (ep 8)", "#09: \"Motteke! Taisou Fuku (\u3082\u3063\u3066\u3051\uff01\u4f53\u64cd\u3075\u304f)\" by Kana Asumi (ep 9)", "#10: \"Mahou no Kotoba: Osaka\u2010Ben (\u9b54\u6cd5\u306e\u8a00\u8449\u301cOsaka-Ben\u301c)\" by Kana Asumi (ep 10)", "#11: \"Omrice no Onna (\u30aa\u30e0\u30e9\u30a4\u30b9\u306e\u5973)\" by Kana Asumi (ep 11)", "#12: \"LA LA LA OINARI SONG (LA\u30fbLA\u30fbLA\u30fbOINARI SONG)\" by Kana Asumi (ep 12)"], "image": "https://api-cdn.myanimelist.net/images/anime/12/45352.jpg"}