{"show_name": "Boukyaku no Senritsu", "other_title": ["The Melody of Oblivion", "\u5fd8\u5374\u306e\u65cb\u5f8b"], "genre": ["Adventure", "Fantasy", "Horror", "Mecha", "Psychological", "Sci-Fi", "Shounen", "Space", "Supernatural"], "type": "tv", "plot": "", "episode": 24, "vintage": "2004-04-07 - 2004-09-22", "opening_theme": ["\"Will\" by Lisa Komine"], "ending_theme": ["\"Tenohira no Hikari (\u3066\u306e\u3072\u3089\u306e\u5149)\" by Minawo"], "image": "https://api-cdn.myanimelist.net/images/anime/9/52679.jpg"}