{"show_name": "THE iDOLM@STER Cinderella Girls: Starlight Stage - Shinshun! Happy New Year Campaign", "other_title": ["\u30a2\u30a4\u30c9\u30eb\u30de\u30b9\u30bf\u30fc \u30b7\u30f3\u30c7\u30ec\u30e9\u30ac\u30fc\u30eb\u30ba \u30b9\u30bf\u30fc\u30e9\u30a4\u30c8\u30b9\u30c6\u30fc\u30b8 \u65b0\u6625\uff01\u30cf\u30c3\u30d4\u30fc\u30cb\u30e5\u30fc\u30a4\u30e4\u30fc\u30ad\u30e3\u30f3\u30da\u30fc\u30f3"], "genre": ["Game", "Music"], "type": "special", "plot": "", "episode": 1, "vintage": "2017-12-31 - 2017-12-31", "opening_theme": [], "ending_theme": [], "image": "https://api-cdn.myanimelist.net/images/anime/3/90095.jpg"}