{"show_name": "Key the Metal Idol", "other_title": ["Key the Metal Idol", "KEY THE METAL IDOL"], "genre": ["Action", "Sci-Fi", "Music", "Psychological", "Drama", "Mecha"], "type": "ova", "plot": "", "episode": 15, "vintage": "1994-12-16 - 1997-06-18", "opening_theme": ["\"In the Night\" by Sario Kijima"], "ending_theme": ["#1: \"Watashi ga Soba ni Iru\" by Sario Kijima (eps 1-13)", "#2: \"Passenger\" by Tamiya Terashima (ep 14)", "#3: \"Galaxy in my Hands\" by Junko Iwao (ep 15)"], "image": "https://api-cdn.myanimelist.net/images/anime/5/11220.jpg"}