{"show_name": "3-gatsu no Lion", "other_title": ["Sangatsu no Lion", "March comes in like a lion", "3\u6708\u306e\u30e9\u30a4\u30aa\u30f3"], "genre": ["Drama", "Game", "Seinen", "Slice of Life"], "type": "tv", "plot": "", "episode": 22, "vintage": "2016-10-08 - 2017-03-18", "opening_theme": ["#1: \"Answer (\u30a2\u30f3\u30b5\u30fc)\" by BUMP OF CHICKEN (eps 1-11)", "#2: \"Sayonara Bystander (\u3055\u3088\u306a\u3089\u30d0\u30a4\u30b9\u30bf\u30f3\u30c0\u30fc)\" by YUKI (eps 12-22)"], "ending_theme": ["#1: \"Fighter (\u30d5\u30a1\u30a4\u30bf\u30fc)\" by BUMP OF CHICKEN (eps 1-6, 8-11, 22)", "#2: \"Nyaa Shougi Ondo (\u30cb\u30e3\u30fc\u5c06\u68cb\u97f3\u982d)\" by Hinata (Kana Hanazawa), Akari (Ai Kayano), Momo (Misaki Kuno) (ep 7)", "#3: \"orion\" by Kenshi Yonezu (\u7c73\u6d25 \u7384\u5e2b) (eps 12-21)"], "image": "https://api-cdn.myanimelist.net/images/anime/6/82898.jpg"}