{"show_name": "Hikyou Tanken Fam & Ihrlie", "other_title": ["Ruin Explorers: Quest for the Ultimate Power", "Ruin Explorers Fam & Ihrie", "\u79d8\u5883\u63a2\u691c \u30d5\u30a1\u30e0\uff06\u30a4\u30fc\u30ea\u30fc"], "genre": ["Action", "Adventure", "Comedy", "Fantasy", "Magic"], "type": "ova", "plot": "", "episode": 4, "vintage": "1995-06-25 - 1996-02-25", "opening_theme": ["\"Magical Beat\" by Rica Matsumoto"], "ending_theme": ["#1: \"Dear Myself - A Time Capsule to Myself\" by Kumi Konno (eps 1-3)", "#2: \"Magical Beat\" by Rica Matsumoto (ep 4)"], "image": "https://api-cdn.myanimelist.net/images/anime/1775/92278.jpg"}