{"show_name": "Chio-chan no Tsuugakuro", "other_title": ["Chio's School Road", "\u3061\u304a\u3061\u3083\u3093\u306e\u901a\u5b66\u8def"], "genre": ["Comedy", "Seinen"], "type": "tv", "plot": "", "episode": 12, "vintage": "2018-07-06 - 2018-09-21", "opening_theme": ["\"Danger in my Tsuugakuro (Danger in my \u901a\u5b66\u8def)\" by Chio Miyamo (CV: Naomi Oozora), Manana Nonomura (CV: Chiaki Omigawa), and Yuki Hosokawa (CV: Kaede Hondo)"], "ending_theme": ["\"Nanairoad (\u30ca\u30ca\u30a4\u30ed\u30fc\u30c9)\" by Chio Miyamo (CV: Naomi Oozora) and Manana Nonomura (CV: Chiaki Omigawa)"], "image": "https://api-cdn.myanimelist.net/images/anime/1073/95042.jpg"}