{"show_name": "Selector Infected WIXOSS", "other_title": ["selector infected WIXOSS", "selector infected WIXOSS"], "genre": ["Game", "Psychological"], "type": "tv", "plot": "", "episode": 12, "vintage": "2014-04-04 - 2014-06-20", "opening_theme": ["\"killy killy JOKER\" by Kanon Wakeshima"], "ending_theme": ["#1: \"realize -Yume no Matsu Basho- (realize -\u5922\u306e\u5f85\u3064\u5834\u6240-)\" by Cyua (eps 1-10)", "#2: \"realize -Yume no Matsu Basho- ~White Hope mix~  (realize -\u5922\u306e\u5f85\u3064\u5834\u6240- ~White Hope mix~)\" by Cyua (ep 11)"], "image": "https://api-cdn.myanimelist.net/images/anime/13/70147.jpg"}