{"show_name": "Coo: Tooi Umi kara Kita Coo", "other_title": ["Coo of the Far Seas", "Coo: Come From a Distant Ocean Coo", "Coo \u9060\u3044\u6d77\u304b\u3089\u6765\u305f\u30af\u30fc"], "genre": ["Adventure", "Slice of Life", "Mystery", "Drama"], "type": "movie", "plot": "", "episode": 1, "vintage": "1993-12-19 - 1993-12-19", "opening_theme": [], "ending_theme": ["\"Zutto Soba ni (\u305a\u3063\u3068\u305d\u3070\u306b)\" by Yumi Matsutoya"], "image": "https://api-cdn.myanimelist.net/images/anime/2/49723.jpg"}