{"show_name": "Tennis no Ouji-sama: Sonzoku Yama no Hi", "other_title": ["Tennis no Ouji-sama", "Prince of Tennis: Jump Festa 2002 - A Day of the Survival Mountain", "Prince of Tennis: A Day of the Survival Mountain", "\u30c6\u30cb\u30b9\u306e\u738b\u5b50: \u5b58\u7d9a\u5c71\u306e\u65e5"], "genre": ["Adventure", "Comedy", "Sports", "Shounen"], "type": "ova", "plot": "", "episode": 1, "vintage": "2003 - 2003", "opening_theme": [], "ending_theme": [], "image": "https://api-cdn.myanimelist.net/images/anime/10/4471.jpg"}