{"show_name": "Taka no Tsume-dan Yoshida Presents \"Sengoku Taiga\" no Susume", "other_title": ["Eagle Talon", "Himitsukessha Taka no Tsume", "The Frogman Show", "Taka no Tsume-dan ga \"Sengoku Taiga\" de Tenka Touitsu Mezashite Mita!", "\u9df9\u306e\u722a\u56e3\u5409\u7530\u30d7\u30ec\u30bc\u30f3\u30c4 \u300e\u6226\u56fd\u5927\u6cb3\u300f \u306e\u30b9\u30b9\u30e1"], "genre": ["Comedy", "Game", "Parody", "Samurai"], "type": "ona", "plot": "", "episode": 1, "vintage": "2019-04-24 - 2019-04-24", "opening_theme": [], "ending_theme": [], "image": "https://api-cdn.myanimelist.net/images/anime/1927/100771.jpg"}