{"show_name": "Kaitei Shounen Marine", "other_title": ["Undersea Boy Marine", "Marine Boy", "\u6d77\u5e95\u5c11\u5e74\u30de\u30ea\u30f3"], "genre": ["Action", "Adventure", "Kids", "Sci-Fi"], "type": "tv", "plot": "", "episode": 65, "vintage": "1969-01-13 - 1971-09-02", "opening_theme": ["\"Kaitei Shounen Marine (Go Go Marine) (\u6d77\u5e95\u5c11\u5e74\u30de\u30ea\u30f3(\u30b4\u30fc\u30b4\u30fc\u30fb\u30de\u30ea\u30f3))\" by Niriko Ohara, Wakakusa Jidou Gasshoudan"], "ending_theme": [], "image": "https://api-cdn.myanimelist.net/images/anime/13/24677.jpg"}