{"show_name": "Itoshi no Muco", "other_title": ["Lovely Muco!", "Itoshi no Muuco", "Lovely Muuuuuuuco!", "\u3044\u3068\u3057\u306e\u30e0\u30fc\u30b3"], "genre": ["Slice of Life", "Comedy"], "type": "tv", "plot": "", "episode": 25, "vintage": "2015-10-03 - 2016-03-26", "opening_theme": ["\"SUKI!SUKI!SUKI!\" by Muco (Hitomi Yoshida)"], "ending_theme": ["#1: \"Basyauma Rock\" by Team Syachihoko", "#2: \"Dreamer\" by Tomohisa Yamashita"], "image": "https://api-cdn.myanimelist.net/images/anime/10/76473.jpg"}