{"show_name": "18if", "other_title": ["18 If", "18if", "18if"], "genre": ["Mystery", "Supernatural"], "type": "tv", "plot": "", "episode": 13, "vintage": "2017-07-07 - 2017-09-29", "opening_theme": ["\"Red Doors feat. Yoshikazu Mera (Red Doors feat.\u7c73\u826f\u7f8e\u4e00) by TeddyLoid"], "ending_theme": ["#01: \"Wonderland\" by Lily (Kaori Nazuka) (ep 1)", "#02: \"Break The Doors feat. Aina The End (BiSH)\" by TeddyLoid (ep 2)", "#03: \"Yume Koibana (\u5922\u604b\u82b1)\" by Kayo Sugisaki (Nao Tamura) (ep 3)", "#04: \"ANGELNOIR\" by Ichiko Aoba (\u9752\u8449\u5e02\u5b50) (ep 4)", "#05: \"Plumeria (\u30d7\u30eb\u30e1\u30ea\u30a2)\" by Aki Okui (ep 5)", "#06: \"Yukue Shirezu (\u884c\u65b9\u77e5\u30ec\u30ba)\" by Gesshoku Kaigi (\u6708\u8755\u6703\u8b70) (ep 6)", "#07: \"too late\" by Nene (Inori Minase) (ep 7)", "#08: \"Sora no Oto (\u7a7a\u306e\u97f3)\" by Ryu Miho (ep 8)", "#09: \"Tsubasa (\u30c4\u30d0\u30b5)\" by Misaki (Emi Nitta) (ep 9)", "#10: \"Factor Word (\u30d5\u30a1\u30af\u30bf\u30fc\u30fb\u30ef\u30fc\u30c9)\" by a-Mujigen (Shiho Nanba) (ep 10)", "#11: \"Salvation\" by TeddyLoid (ep 11)", "#12: \"Shiratori wa Nemuru feat. Yoshikazu Mera (\u767d\u9ce5\u306f\u7720\u308b feat.\u7c73\u826f\u7f8e\u4e00)\" by TeddyLoid (ep 12)", "#13: \"if\" by Haruto Tsukishiro (Nobunaga Shimazaki) (ep 13)"], "image": "https://api-cdn.myanimelist.net/images/anime/7/86743.jpg"}