{"show_name": "Tokyo One Piece Tower: Tongari Shima no Dai Hihou", "other_title": ["The Great Tongari Island Treasure Hunting Adventure", "Treasure Hunting: Tongari Shima no Daibouken", "\u6771\u4eac\u30ef\u30f3\u30d4\u30fc\u30b9\u30bf\u30ef\u30fc \u30c8\u30f3\u30ac\u30ea\u5cf6\u306e\u5927\u79d8\u5b9d"], "genre": ["Action", "Adventure", "Super Power", "Shounen"], "type": "movie", "plot": "", "episode": 1, "vintage": "2016-11-01 - 2016-11-01", "opening_theme": [], "ending_theme": [], "image": "https://api-cdn.myanimelist.net/images/anime/1203/95013.jpg"}