{"show_name": "Shuffle! Memories", "other_title": ["\u30b7\u30e3\u30c3\u30d5\u30eb\uff01\u30e1\u30e2\u30ea\u30fc\u30ba"], "genre": ["Comedy", "Drama", "Ecchi", "Fantasy", "Harem", "Magic", "Romance", "School", "Seinen"], "type": "tv", "plot": "", "episode": 12, "vintage": "2007-01-08 - 2007-03-26", "opening_theme": ["#1: \"Fateful Encounters\" by YURIA (ep 1)", "#2: \"memories\" by Yuko Goto (eps 2,7)", "#3: \"High Tension Dreamer\" by Miki Itou (eps 3,8)", "#4: \"pray\" by Haruka Nagami (eps 4,9)", "#5: \"Giri Giri Heart Connection (\u304e\u308a\u304e\u308aHeart\u30b3\u30cd\u30af\u30b7\u30e7\u30f3)\" by Sayaka Aoki (eps 5,10)", "#6: \"pureness\" by Hitomi (eps 6,11)"], "ending_theme": ["#1: \"innocence\" by Miyuki Hashimoto (ep 1)", "#2: \"only one, only love\" by Yuko Goto (eps 2,7)", "#3: \"wish\" by Miki Itou (eps 3,8)", "#4: \"Himitsu no Mori (\u79d8\u5bc6\u306e\u68ee)\" by Haruka Nagami (eps 4,9)", "#5: \"freedom\" by Sayaka Aoki (eps 5,10)", "#6: \"Magical*Power Station (\u307e\u3058\u304b\u308b\u2606\u30d1\u30ef\u30fc\u30b9\u30c6\u30fc\u30b7\u30e7\u30f3)\" by Hitomi (eps 6,11)", "#7: \"natural tone\" by Miyuki Hashimoto (ep 12)"], "image": "https://api-cdn.myanimelist.net/images/anime/4/19624.jpg"}