{"show_name": "Silk Road Shounen Yuuto: Toki wo Kakeru Shounen Yuuto no Hyouryuu Nikki", "other_title": ["Silk Road Shounen Yuuto Omnibus", "Silk Road Shounen Yuuto Recap", "Silk Road Boy Yuto Soushuuhen", "Silk Road Shounen Yuto Omnibus", "Silk Road Shounen Yuto Recap", "Silk Road Shounen Yuto: Toki wo Kakeru Shounen Yuto no Hyouryuu Nikki", "\u30b7\u30eb\u30af\u30ed\u30fc\u30c9\u5c11\u5e74 \u30e6\u30fc\u30c8 \u7dcf\u96c6\u7de8"], "genre": ["Adventure", "Fantasy", "Historical"], "type": "special", "plot": "", "episode": 1, "vintage": "2007-01-13 - 2007-01-13", "opening_theme": [], "ending_theme": [], "image": "https://api-cdn.myanimelist.net/images/anime/4/77689.jpg"}