{"show_name": "Ashita e Attack!", "other_title": ["Smash", "Attack on Tomorrow", "\u3042\u3057\u305f\u3078\u30a2\u30bf\u30c3\u30af\uff01"], "genre": ["Sports", "School", "Drama"], "type": "tv", "plot": "", "episode": 23, "vintage": "1977-04-04 - 1977-09-05", "opening_theme": ["\"Ashita e Attack (\u3042\u3057\u305f\u3078\u30a2\u30bf\u30c3\u30af)\" by Mitsuko Horie"], "ending_theme": ["\"Volleyball ga Suki (\u30d0\u30ec\u30fc\u30dc\u30fc\u30eb\u304c\u597d\u304d)\" by Mitsuko Horie"], "image": "https://api-cdn.myanimelist.net/images/anime/5/8206.jpg"}