{"show_name": "Mini Hama: Minimum Hamatora Movies", "other_title": ["Minimum-Hamatora", "Mini Hama Gekijouban Specials", "Mini Hama Episodes 9 and 10", "\u5287\u5834\u7248 \u30df\u30cb\u306f\u307e -MINIMUM HAMATORA-"], "genre": ["Comedy", "Mystery", "School", "Super Power"], "type": "movie", "plot": "", "episode": 2, "vintage": "2015-11-14 - 2015-11-14", "opening_theme": [], "ending_theme": ["\"Little Crazy\" by Hamatora: Nice & Murasaki (Ryota Osaka & Wataru Hatano)"], "image": "https://api-cdn.myanimelist.net/images/anime/7/76836.jpg"}