{"show_name": "Bakemonogatari Recap", "other_title": ["Bakemonogatari Episode 5.5", "Bakemonogatari Special", "Ghostory Recap", "Ghostory Special", "\u5316\u7269\u8a9e"], "genre": ["Mystery", "Romance", "Supernatural"], "type": "special", "plot": "", "episode": 1, "vintage": "2009-08-07 - 2009-08-07", "opening_theme": [], "ending_theme": ["\"Kimi no Shiranai Monogatari (\u541b\u306e\u77e5\u3089\u306a\u3044\u7269\u8a9e)\" by supercell; performed by Gazelle"], "image": "https://api-cdn.myanimelist.net/images/anime/11/65863.jpg"}