{"show_name": "Utawarerumono", "other_title": ["The One Being Sung", "Utawarerumono", "\u3046\u305f\u308f\u308c\u308b\u3082\u306e"], "genre": ["Action", "Drama", "Fantasy", "Sci-Fi"], "type": "tv", "plot": "", "episode": 26, "vintage": "2006-04-04 - 2006-09-26", "opening_theme": ["\"Musouka (\u5922\u60f3\u6b4c)\" by Suara"], "ending_theme": ["#1: \"Madoromi no Rinne (\u307e\u3069\u308d\u307f\u306e\u8f2a\u5efb)\" by Eri Kawai (eps 1-25)", "#2: \"Kimi ga Tame (\u30ad\u30df\u30ac\u30bf\u30e1)\" by Suara (ep 26)"], "image": "https://api-cdn.myanimelist.net/images/anime/9/24605.jpg"}