{"show_name": "Puzzle & Dragon", "other_title": ["PazuDora", "Puzzle & Dragon", "\u30d1\u30ba\u30c9\u30e9"], "genre": ["Game", "Kids"], "type": "tv", "plot": "", "episode": 0, "vintage": "currently airing", "opening_theme": ["#1: \"Everybody GO!\" by Taiga Akashi (Asuna Tomari) (eps 1-59)", "#2: \"Hallelujah lu-jah (\u30cf\u30ec\u30eb\u30e4\u30eb\u30fc\u30e4)\" by Daisuke Yokoyama (\u6a2a\u5c71\u3060\u3044\u3059\u3051) (eps 60-)"], "ending_theme": ["#1: \"\u25b6START\" by Mahou Shoujo ni Nari-tai (\u9b54\u6cd5\u5c11\u5973\u306b\u306a\u308a\u968a) (eps 1-26)", "#2: \"Tr\u00e4umerei (\u30c8\u30ed\u30a4\u30e1\u30e9\u30a4)\" by Mahou Shoujo ni Nari-tai (eps 27-51)", "#3: \"Smash Drop (\u30b9\u30de\u30c3\u30b7\u30e5\u30fb\u30c9\u30ed\u30c3\u30d7)\" by Momo Asakura (eps 52-64)", "#4: \"GET OVER\" by Mashiro Ayano (eps 65-78)", "#5: \"Friendship No.1 (\u30d5\u30ec\u30f3\u30c9\u30b7\u30c3\u30d7No.1)\" by Misaki Kurea from Girls\u00b2 (\u30df\u30b5\u30ad\u30af\u30ec\u30a2 from Girls\u00b2) (eps 79-90)", "#6: \"PEACE!!\" by Luna Haruna (eps 91-103)", "#7: \"MATSURI!!\" by Kaoru Wada (eps 104-)"], "image": "https://api-cdn.myanimelist.net/images/anime/1535/95070.jpg"}