{"show_name": "Space\u2606Dandy", "other_title": ["Space Dandy", "\u30b9\u30da\u30fc\u30b9\u2606\u30c0\u30f3\u30c7\u30a3"], "genre": ["Sci-Fi", "Space", "Comedy"], "type": "tv", "plot": "", "episode": 13, "vintage": "2014-01-05 - 2014-03-27", "opening_theme": ["\"Viva Namida (\u30d3\u30d0\u30ca\u30df\u30c0)\" by Yasuyuki Okamura"], "ending_theme": ["\"X Jigen e Youkoso (X\u6b21\u5143\u3078\u3088\u3046\u3053\u305d)\" by Etsuko Yakushimaru"], "image": "https://api-cdn.myanimelist.net/images/anime/4/56611.jpg"}