{"show_name": "Darker than Black: Kuro no Keiyakusha", "other_title": ["DTB", "Darker than Black", "Darker than BLACK -\u9ed2\u306e\u5951\u7d04\u8005-"], "genre": ["Action", "Sci-Fi", "Mystery", "Super Power"], "type": "tv", "plot": "", "episode": 25, "vintage": "2007-04-06 - 2007-09-28", "opening_theme": ["#01: \"Howling\" by Abingdon Boys School (eps 1-14)", "#02: \"Kakusei Heroism ~The Hero without a Name~\" by An Cafe (eps 15-23, 25)"], "ending_theme": ["#01: \"Tsuki Akari\" by Rie Fu (eps 1-14)", "#02: \"Dreams\" by HIGH and MIGHTY COLOR (eps 15-24)"], "image": "https://api-cdn.myanimelist.net/images/anime/5/19570.jpg"}