{"show_name": "Free!: Eternal Summer - Kindan no All Hard!", "other_title": ["Free!: Eternal Summer Special", "Free!: Iwatobi Swim Club 2 Special", "Free! 2nd Season Special", "Free! -Eternal Summer- \u7981\u65ad\u306e\u30aa\u30fc\u30eb\u30cf\u30fc\u30c9\uff01"], "genre": ["Comedy", "School", "Slice of Life"], "type": "special", "plot": "", "episode": 1, "vintage": "2015-03-18 - 2015-03-18", "opening_theme": ["\"Dried Up Youthful Fame\" by OLDCODEX"], "ending_theme": ["\"FUTURE FISH\" by STYLE FIVE (Nobunaga Shimazaki, Tatsuhisa Suzuki, Mamoru Miyano, Tsubasa Yonaga, Daisuke Hirakawa)"], "image": "https://api-cdn.myanimelist.net/images/anime/6/73125.jpg"}