{"show_name": "Mahoutsukai no Yome: Hoshi Matsu Hito", "other_title": ["The Magician's Bride", "The Ancient Magus' Bride: Those Awaiting a Star", "\u9b54\u6cd5\u4f7f\u3044\u306e\u5ac1 \u661f\u5f85\u3064\u3072\u3068"], "genre": ["Slice of Life", "Magic", "Fantasy", "Shounen"], "type": "ova", "plot": "", "episode": 3, "vintage": "2016-09-10 - 2017-09-09", "opening_theme": [], "ending_theme": ["\"CLOCKWORK QUICK AND LIGHTNING SLOW\" by Julia Shortreed"], "image": "https://api-cdn.myanimelist.net/images/anime/4/80587.jpg"}