{"show_name": "Ginga Eiyuu Densetsu Gaiden: Ougon no Tsubasa", "other_title": ["Legend of the Galactic Heroes Gaiden: Golden Wings", "LoGH Gaiden: Golden Wings", "Legend of the Galactic Heroes MOVIE (1992)", "\u9280\u6cb3\u82f1\u96c4\u4f1d\u8aac\u5916\u4f1d\u3000\u9ec4\u91d1\u306e\u7ffc"], "genre": ["Action", "Military", "Sci-Fi", "Space", "Drama"], "type": "movie", "plot": "", "episode": 1, "vintage": "1992-12-12 - 1992-12-12", "opening_theme": [], "ending_theme": ["\"Futari Mita Yume ~Two of Us~ (\u3075\u305f\u308a\u898b\u305f\u5922 ~TWO OF US~)\" by Hiroyuki Matsuda"], "image": "https://api-cdn.myanimelist.net/images/anime/7/52221.jpg"}