{"show_name": "Kinnikuman II Sei: Ultimate Muscle 2", "other_title": ["Kinnikuman Nisei: Ultimate Muscle 2", "\u30ad\u30f3\u8089\u30de\u30f3II\u4e16 ULTIMATE MUSCLE 2"], "genre": ["Action", "Sci-Fi", "Comedy", "Sports", "Martial Arts", "Shounen"], "type": "tv", "plot": "", "episode": 13, "vintage": "2006-01-04 - 2006-03-29", "opening_theme": ["\"Trust yourself\" by Takatori Hideaki"], "ending_theme": ["\"Chikai no Tsuki (\u8a93\u30ce\u6708)\" by Kagrra"], "image": "https://api-cdn.myanimelist.net/images/anime/10/14986.jpg"}